robofin/__init__.py
robofin/_version.py
robofin/bullet.py
robofin/collision.py
robofin/geometry.py
robofin/meshcat.py
robofin/point_cloud_tools.py
robofin/robot_constants.py
robofin/robots.py
robofin/samplers.py
robofin/torch_urdf.py
robofin/cache/point_cloud/franka/franka_point_cloud_1024_128.npy
robofin/cache/point_cloud/franka/franka_point_cloud_2048_128.npy
robofin/cache/point_cloud/franka/franka_point_cloud_4096_128.npy
robofin/kinematics/__init__.py
robofin/kinematics/numba.py
robofin/kinematics/torch.py
robofin/kinematics/__pycache__/numba.axis_angle-10.py310.1.nbc
robofin/kinematics/__pycache__/numba.axis_angle-10.py310.2.nbc
robofin/kinematics/__pycache__/numba.axis_angle-10.py310.nbi
robofin/kinematics/__pycache__/numba.axis_angle-11.py310.1.nbc
robofin/kinematics/__pycache__/numba.axis_angle-11.py310.2.nbc
robofin/kinematics/__pycache__/numba.axis_angle-11.py310.nbi
robofin/kinematics/__pycache__/numba.axis_angle-68.py38.1.nbc
robofin/kinematics/__pycache__/numba.axis_angle-68.py38.nbi
robofin/kinematics/__pycache__/numba.axis_angle-69.py38.1.nbc
robofin/kinematics/__pycache__/numba.axis_angle-69.py38.2.nbc
robofin/kinematics/__pycache__/numba.axis_angle-69.py38.nbi
robofin/kinematics/__pycache__/numba.axis_angle-70.py310.1.nbc
robofin/kinematics/__pycache__/numba.axis_angle-70.py310.2.nbc
robofin/kinematics/__pycache__/numba.axis_angle-70.py310.nbi
robofin/kinematics/__pycache__/numba.axis_angle-70.py38.1.nbc
robofin/kinematics/__pycache__/numba.axis_angle-70.py38.2.nbc
robofin/kinematics/__pycache__/numba.axis_angle-70.py38.3.nbc
robofin/kinematics/__pycache__/numba.axis_angle-70.py38.nbi
robofin/kinematics/__pycache__/numba.eef_pose_to_link8-383.py310.1.nbc
robofin/kinematics/__pycache__/numba.eef_pose_to_link8-383.py310.nbi
robofin/kinematics/__pycache__/numba.eef_pose_to_link8-427.py310.1.nbc
robofin/kinematics/__pycache__/numba.eef_pose_to_link8-427.py310.nbi
robofin/kinematics/__pycache__/numba.eef_pose_to_link8-441.py38.1.nbc
robofin-0.0.4.4.dist-info/LICENSE
robofin-0.0.4.4.dist-info/METADATA
robofin-0.0.4.4.dist-info/WHEEL
robofin-0.0.4.4.dist-info/top_level.txt
robofin-0.0.4.4.dist-info/RECORD
