Metadata-Version: 2.1
Name: robofin
Version: 0.0.4.4
Summary: A collection of robotics tools tailored to machine learning
License: MIT
Requires-Python: >=3.7
License-File: LICENSE
Requires-Dist: pybullet
Requires-Dist: numpy
Requires-Dist: geometrout >=0.1.3
Requires-Dist: torch
Requires-Dist: ikfast-pybind
Requires-Dist: trimesh >=4.0.0
Requires-Dist: urchin >=0.0.27
